mcp_hybrid_search-1.2.2.dist-info/licenses/LICENSE
rag_mcp_server/__init__.py
rag_mcp_server/__main__.py
rag_mcp_server/base.py
rag_mcp_server/pdf.py
rag_mcp_server/server.py
mcp_hybrid_search-1.2.2.dist-info/METADATA
mcp_hybrid_search-1.2.2.dist-info/WHEEL
mcp_hybrid_search-1.2.2.dist-info/entry_points.txt
mcp_hybrid_search-1.2.2.dist-info/top_level.txt
mcp_hybrid_search-1.2.2.dist-info/RECORD
