Metadata-Version: 2.4
Name: mcp-hybrid-search
Version: 1.2.2
Summary: Hybrid Search RAG - A Model Context Protocol (MCP) server for RAG-based document search
Author-email: Jay Pak <jaypark@forestsoft.co.kr>
License: MIT
Project-URL: Homepage, https://forestsoft.co.kr/
Classifier: Programming Language :: Python :: 3
Classifier: License :: OSI Approved :: MIT License
Classifier: Operating System :: OS Independent
Requires-Python: >=3.12
License-File: LICENSE
Requires-Dist: mcp
Requires-Dist: langchain
Requires-Dist: langchain-experimental
Requires-Dist: langchain-openai
Requires-Dist: langchain-chroma
Requires-Dist: langchain-community
Requires-Dist: pypdf
Requires-Dist: rank_bm25
Requires-Dist: pdfplumber
Dynamic: license-file
